prt_sim/__init__.py
prt_sim/common/__init__.py
prt_sim/common/grid_rendering.py
prt_sim/gymnasium/__init__.py
prt_sim/gymnasium/image_pipeline.py
prt_sim/gymnasium/toolbox.py
prt_sim/jhu/__init__.py
prt_sim/jhu/bandits.py
prt_sim/jhu/base.py
prt_sim/jhu/blackjack.py
prt_sim/jhu/gold_explorer.py
prt_sim/jhu/plot.py
prt_sim/jhu/registry.py
prt_sim/jhu/robot_game.py
prt_sim/jhu/icons/coins.png
prt_sim/jhu/icons/explorer.png
prt_sim/jhu/icons/fred.png
prt_sim/jhu/icons/gold.png
prt_sim/jhu/icons/mine.png
prt_sim/jhu/icons/mountain.png
prt_sim/jhu/icons/obstacle.png
prt_sim/jhu/icons/outlet.png
prt_sim/jhu/icons/pit.png
prt_sim-0.1.8.dist-info/METADATA
prt_sim-0.1.8.dist-info/WHEEL
prt_sim-0.1.8.dist-info/entry_points.txt
prt_sim-0.1.8.dist-info/licenses/LICENSE
prt_sim-0.1.8.dist-info/RECORD
