Metadata-Version: 2.4
Name: prt-sim
Version: 0.1.8
Summary: Python Research Toolkit - Simulation
Author-email: Gavin Strunk <gavin.strunk@gmail.com>
License-File: LICENSE
Requires-Python: >=3.11
Requires-Dist: gymnasium>=1.2.0
Requires-Dist: matplotlib>=3.10.1
Requires-Dist: numpy>=2.2.3
Requires-Dist: prt-datasets>=0.1.1
Requires-Dist: prt-nn>=0.1.1
Requires-Dist: pycocotools>=2.0.10
Requires-Dist: pygame>=2.6.1
Requires-Dist: scikit-image>=0.25.2
Requires-Dist: torchmetrics>=1.8.2
Requires-Dist: torchvision>=0.23.0
Requires-Dist: ultralytics>=8.3.207
